flexidep/DependencyManager.py
flexidep/__init__.py
flexidep/cli.py
flexidep/config.py
flexidep/core.py
flexidep/exceptions.py
flexidep/gui.py
flexidep/installers.py
flexidep/utils.py
flexidep-0.0.9.dist-info/LICENSE
flexidep-0.0.9.dist-info/METADATA
flexidep-0.0.9.dist-info/WHEEL
flexidep-0.0.9.dist-info/top_level.txt
flexidep-0.0.9.dist-info/RECORD
