Metadata-Version: 2.1
Name: flexidep
Version: 0.0.9
Summary: Managing dependencies for other python packages, especially when multiple alternatives exist for the same module.
Author: Francesco Santini
Author-email: francesco.santini@gmail.com
License: Apache License 2.0
Keywords: Package management,dependency management,package manager,dependency manager
Classifier: Programming Language :: Python :: 3
Requires-Python: >=3.7
License-File: LICENSE
Requires-Dist: packaging
Requires-Dist: appdirs
Requires-Dist: importlib-resources ; python_version < "3.10"
